hektor.py
hektor-0.3.6.data/scripts/hektor
lib/__init__.py
lib/generic.py
lib/identity.py
lib/qti.py
lib/xls.py
hektor-0.3.6.dist-info/LICENSE
hektor-0.3.6.dist-info/METADATA
hektor-0.3.6.dist-info/WHEEL
hektor-0.3.6.dist-info/top_level.txt
hektor-0.3.6.dist-info/RECORD
