Metadata-Version: 2.1
Name: hektor
Version: 0.3.6
Summary: A QTI-XML/XLS to JSON converter for humans
Home-page: https://gitlab.gwdg.de/j.michal/hektor
Author: Jan Maximilian Michal
Author-email: mail@janmax.org
License: MIT
Platform: UNKNOWN
Requires-Dist: lxml (~=4.1.1)
Requires-Dist: xlrd (~=1.1.0)
Requires-Dist: xkcdpass (~=1.16.0)
